odoo9_addon_website_portal_sale_v10-9.0.1.0.0.99.dev12-py3.8-nspkg.pth
odoo_addons/website_portal_sale_v10/README.rst
odoo_addons/website_portal_sale_v10/__init__.py
odoo_addons/website_portal_sale_v10/__openerp__.py
odoo_addons/website_portal_sale_v10/controllers/__init__.py
odoo_addons/website_portal_sale_v10/controllers/main.py
odoo_addons/website_portal_sale_v10/i18n/af.po
odoo_addons/website_portal_sale_v10/i18n/ar.po
odoo_addons/website_portal_sale_v10/i18n/bg.po
odoo_addons/website_portal_sale_v10/i18n/bs.po
odoo_addons/website_portal_sale_v10/i18n/ca.po
odoo_addons/website_portal_sale_v10/i18n/cs.po
odoo_addons/website_portal_sale_v10/i18n/da.po
odoo_addons/website_portal_sale_v10/i18n/de.po
odoo_addons/website_portal_sale_v10/i18n/el.po
odoo_addons/website_portal_sale_v10/i18n/el_GR.po
odoo_addons/website_portal_sale_v10/i18n/en_GB.po
odoo_addons/website_portal_sale_v10/i18n/es.po
odoo_addons/website_portal_sale_v10/i18n/es_AR.po
odoo_addons/website_portal_sale_v10/i18n/es_BO.po
odoo_addons/website_portal_sale_v10/i18n/es_CL.po
odoo_addons/website_portal_sale_v10/i18n/es_CO.po
odoo_addons/website_portal_sale_v10/i18n/es_CR.po
odoo_addons/website_portal_sale_v10/i18n/es_DO.po
odoo_addons/website_portal_sale_v10/i18n/es_EC.po
odoo_addons/website_portal_sale_v10/i18n/es_MX.po
odoo_addons/website_portal_sale_v10/i18n/es_PE.po
odoo_addons/website_portal_sale_v10/i18n/es_PY.po
odoo_addons/website_portal_sale_v10/i18n/es_VE.po
odoo_addons/website_portal_sale_v10/i18n/et.po
odoo_addons/website_portal_sale_v10/i18n/eu.po
odoo_addons/website_portal_sale_v10/i18n/fa.po
odoo_addons/website_portal_sale_v10/i18n/fi.po
odoo_addons/website_portal_sale_v10/i18n/fo.po
odoo_addons/website_portal_sale_v10/i18n/fr.po
odoo_addons/website_portal_sale_v10/i18n/fr_CA.po
odoo_addons/website_portal_sale_v10/i18n/fr_FR.po
odoo_addons/website_portal_sale_v10/i18n/gl.po
odoo_addons/website_portal_sale_v10/i18n/he.po
odoo_addons/website_portal_sale_v10/i18n/hr.po
odoo9_addon_website_portal_sale_v10-9.0.1.0.0.99.dev12.dist-info/METADATA
odoo9_addon_website_portal_sale_v10-9.0.1.0.0.99.dev12.dist-info/WHEEL
odoo9_addon_website_portal_sale_v10-9.0.1.0.0.99.dev12.dist-info/namespace_packages.txt
odoo9_addon_website_portal_sale_v10-9.0.1.0.0.99.dev12.dist-info/top_level.txt
odoo9_addon_website_portal_sale_v10-9.0.1.0.0.99.dev12.dist-info/RECORD
